pyjapt/__init__.py
pyjapt/automata.py
pyjapt/lexing.py
pyjapt/parsing.py
pyjapt/serialization.py
pyjapt/typing.py
pyjapt/utils.py
pyjapt-0.4.1.dist-info/LICENSE
pyjapt-0.4.1.dist-info/WHEEL
pyjapt-0.4.1.dist-info/METADATA
pyjapt-0.4.1.dist-info/RECORD
