Metadata-Version: 2.1
Name: pyjapt
Version: 0.4.1
Summary: Just Another Parsing Tool Written in Python
Home-page: https://github.com/alejandroklever/PyJapt
Author: Alejandro Klever
Author-email: alejandroklever@alejandroklever.dev
Requires-Python: >=3.10,<4.0
Classifier: Programming Language :: Python :: 3
Classifier: Programming Language :: Python :: 3.10
Classifier: Programming Language :: Python :: 3.11
Requires-Dist: flake8 (>=6.0.0,<7.0.0)
